{
  "id": "noble-longsword",
  "name": "Noble Longsword",
  "nameZh": "贵族长剑",
  "slot": "2hsword",
  "tier": 5,
  "rarity": "common",
  "material": "metal",
  "image": "/images/weapons/two-handed-swords/noble-longsword.webp",
  "durability": 170,
  "price": 8425,
  "properties": {
    "accuracy": 10,
    "armorPenetration": 20,
    "blockChance": 12,
    "staggerChance": 30,
    "skillsEnergyCost": 35
  },
  "tags": [
    "aldor"
  ],
  "description": "It could have easily belonged to either a small-time baron or a duke - basically the kind of person who doesn't skimp on expanding their arsenal.",
  "descriptionZh": "这把剑本来的主人很有可能是个小地方的男爵，不然就是个公爵，因为这种人扩充军库最舍得花钱。",
  "damage": {
    "value": 32,
    "type": "slashing"
  },
  "range": 1
}