{
  "id": "pyromancer-staff",
  "name": "Pyromancer Staff",
  "nameZh": "炎术长杖",
  "slot": "2hstaff",
  "tier": 4,
  "rarity": "common",
  "material": "metal",
  "image": "/images/weapons/staves/pyromancer-staff.webp",
  "durability": 60,
  "price": 3875,
  "properties": {
    "armorPenetration": 10,
    "skillsEnergyCost": 20,
    "spellsEnergyCost": -4,
    "magicPower": 6,
    "miraclePower": 18,
    "damages": {
      "blunt": 11,
      "fire": 5
    },
    "magicPowers": {
      "pyromantic": 5
    }
  },
  "tags": [
    "magic"
  ],
  "description": "The spherical headpiece radiates extreme heat, which, paradoxically, doesn't seem to cause any harm - at least for the time being...",
  "descriptionZh": "杖头圆球炙热无比，可是好像又不能伤人，起码现在不能……",
  "damage": {
    "value": 11,
    "type": "blunt"
  },
  "range": 1
}